{
	"configurations" : 
	[
		{
			"directories" : 
			[
				{
					"build" : ".",
					"jsonFile" : "directory-.-Debug-f5ebdc15457944623624.json",
					"minimumCMakeVersion" : 
					{
						"string" : "3.6.0"
					},
					"projectIndex" : 0,
					"source" : "."
				}
			],
			"name" : "Debug",
			"projects" : 
			[
				{
					"directoryIndexes" : 
					[
						0
					],
					"name" : "Project"
				}
			],
			"targets" : []
		}
	],
	"kind" : "codemodel",
	"paths" : 
	{
		"build" : "/home/admin/Projects/flutter-test/android/app/.cxx/Debug/6791f4g4/x86_64",
		"source" : "/home/admin/.local/share/flutter/packages/flutter_tools/gradle/src/main/groovy"
	},
	"version" : 
	{
		"major" : 2,
		"minor" : 3
	}
}
